drivescanner/__init__.py
drivescanner/evaluate.py
drivescanner/file_index.py
drivescanner/ingest.py
drivescanner/rules.py
drivescanner/scan.py
drivescanner-0.0.4.dist-info/LICENSE
drivescanner-0.0.4.dist-info/METADATA
drivescanner-0.0.4.dist-info/WHEEL
drivescanner-0.0.4.dist-info/top_level.txt
drivescanner-0.0.4.dist-info/RECORD
