Metadata-Version: 2.1
Name: drivescanner
Version: 0.0.4
Summary: Scan your filesystem to look for files that are a potential GDPR risk
Home-page: https://dev.azure.com/Cmotions/Packages/_git/DriveScanner
Author: Wouter van Gils, Wim Verboom, Sem Frankenberg, Rick Flamand, Jeanine Schoonemann, Kjeld Vissers, Philip Vermeij, Matthijs Otten
Author-email: service@cmotions.nl
Requires-Python: >=3.9
License-File: LICENSE
Requires-Dist: pandas
Requires-Dist: spacy
Requires-Dist: phonenumbers
Requires-Dist: langdetect
Requires-Dist: bs4
Requires-Dist: pypdf (>=3.9.1)
Requires-Dist: tqdm
Requires-Dist: python-pptx
Requires-Dist: docx2txt
Requires-Dist: openpyxl
Provides-Extra: dev
Requires-Dist: black ; extra == 'dev'
Requires-Dist: jupyterlab ; extra == 'dev'
Requires-Dist: pytest (>=6.2.4) ; extra == 'dev'
Requires-Dist: python-dotenv ; extra == 'dev'
Requires-Dist: ipykernel ; extra == 'dev'
Requires-Dist: twine ; extra == 'dev'
Requires-Dist: seaborn ; extra == 'dev'
